[{"_path":"/cv/intro","_dir":"cv","_draft":false,"_partial":false,"_locale":"","title":"Intro","description":"I'm a passionate developer with a strong focus on web development and DevOps. I thrive on learning and working with the latest technologies and frameworks to continuously grow my expertise.","readingTime":{"text":"1 min read","minutes":0.34,"time":20400,"words":68},"_type":"markdown","_id":"content:cv:intro.md","_source":"content","_file":"cv/intro.md","_stem":"cv/intro","_extension":"md","sitemap":{"loc":"/cv/intro"}},{"_path":"/","_dir":"","_draft":false,"_partial":false,"_locale":"","title":"","description":"I'm a passionate developer with a strong focus on web development and DevOps. I thrive on learning and working with the latest technologies and frameworks to continuously grow my expertise. I enjoy collaborating as part of a team in an agile environment, where I can contribute to building impactful solutions. I'm detail-oriented, committed to getting things right, and understand that even the smallest details can make a big difference.","head":{"title":null,"meta":[{"name":"keywords","content":"Steff, Beckers, Developer, Personal website, Blog, Projects, Resume, CV, Home"}]},"readingTime":{"text":"1 min read","minutes":0.385,"time":23100,"words":77},"_type":"markdown","_id":"content:index.md","_source":"content","_file":"index.md","_stem":"index","_extension":"md","sitemap":{"loc":"/","images":[{"loc":"/images/steff.jpg"}]}}]